{"data":{"allCsdbScamDomains":{"edges":[{"node":{"id":"Csdb__ScamDomains__144054","name":"ethbonus.io","url":"http://ethbonus.io","category":"Scamming","subcategory":"Trust-Trading","description":"Trust trading scam site","reporter":"CryptoScamDB","severity":1,"path":"/*","hostname":"ethbonus.io","ip":"","nameservers":[""],"status":"","statusCode":"","updated":1586538939441,"type":"scam","lookups":[""],"abusereport":"","csdbId":"144054","addresses":["0xcEe56C3d77d814d29b9410c0f74c12781fcE03ff"],"grouped_addresses":{"ETH":["0xcEe56C3d77d814d29b9410c0f74c12781fcE03ff"],"BTC":null,"BCH":null,"XRP":null,"TRX":null,"NEO":null,"XMR":null,"LTC":null}}}]}},"pageContext":{"isCreatedByStatefulCreatePages":false,"slug":"144054"}}