{"data":{"allCsdbScamDomains":{"edges":[{"node":{"id":"Csdb__ScamDomains__5653e4","name":"ethereum-airdrop.net","url":"http://ethereum-airdrop.net","category":"Scamming","subcategory":"Trust-Trading","description":"Trust trading scam site","reporter":"CryptoScamDB","severity":1,"path":"/*","hostname":"ethereum-airdrop.net","ip":"","nameservers":[""],"status":"","statusCode":"","updated":1586538939442,"type":"scam","lookups":[""],"abusereport":"","csdbId":"5653e4","addresses":["0xFCB27f1E0bC118014107DaAE776F0aCEeD02e5F3"],"grouped_addresses":{"ETH":["0xFCB27f1E0bC118014107DaAE776F0aCEeD02e5F3"],"BTC":null,"BCH":null,"XRP":null,"TRX":null,"NEO":null,"XMR":null,"LTC":null}}}]}},"pageContext":{"isCreatedByStatefulCreatePages":false,"slug":"5653e4"}}