{"data":{"allCsdbScamDomains":{"edges":[{"node":{"id":"Csdb__ScamDomains__8f5512","name":"myetherwallet.attorney","url":"http://myetherwallet.attorney","category":"Phishing","subcategory":"MyEtherWallet","description":null,"reporter":"CryptoScamDB","severity":1,"path":"/*","hostname":"myetherwallet.attorney","ip":"","nameservers":[""],"status":"","statusCode":"","updated":1586531736502,"type":"scam","lookups":[""],"abusereport":"","csdbId":"8f5512","addresses":[],"grouped_addresses":{"ETH":null,"BTC":null,"BCH":null,"XRP":null,"TRX":null,"NEO":null,"XMR":null,"LTC":null}}}]}},"pageContext":{"isCreatedByStatefulCreatePages":false,"slug":"8f5512"}}