{"data":{"allCsdbScamDomains":{"edges":[{"node":{"id":"Csdb__ScamDomains__1c791e","name":"etnerscan.io","url":"https://etnerscan.io","category":"Phishing","subcategory":"Etherscan","description":"Fake Etherscan site for a fake Monetha ICO address","reporter":"CryptoScamDB","severity":1,"path":"/*","hostname":"etnerscan.io","ip":"","nameservers":[""],"status":"","statusCode":"","updated":1586538939439,"type":"scam","lookups":[""],"abusereport":"","csdbId":"1c791e","addresses":["0x1de23F02E185fDc4f6BACc98D6c6419370E38538"],"grouped_addresses":{"ETH":["0x1de23F02E185fDc4f6BACc98D6c6419370E38538"],"BTC":null,"BCH":null,"XRP":null,"TRX":null,"NEO":null,"XMR":null,"LTC":null}}}]}},"pageContext":{"isCreatedByStatefulCreatePages":false,"slug":"1c791e"}}