{"data":{"allCsdbScamDomains":{"edges":[{"node":{"id":"Csdb__ScamDomains__e40339","name":"myetherwallet.volvo","url":"http://myetherwallet.volvo","category":"Phishing","subcategory":"MyEtherWallet","description":null,"reporter":"CryptoScamDB","severity":1,"path":"/*","hostname":"myetherwallet.volvo","ip":"","nameservers":[""],"status":"","statusCode":"","updated":1586538939438,"type":"scam","lookups":[""],"abusereport":"","csdbId":"e40339","addresses":[],"grouped_addresses":{"ETH":null,"BTC":null,"BCH":null,"XRP":null,"TRX":null,"NEO":null,"XMR":null,"LTC":null}}}]}},"pageContext":{"isCreatedByStatefulCreatePages":false,"slug":"e40339"}}