{"data":{"allCsdbScamDomains":{"edges":[{"node":{"id":"Csdb__ScamDomains__56645e","name":"myetherwallet.compare","url":"http://myetherwallet.compare","category":"Phishing","subcategory":"MyEtherWallet","description":null,"reporter":"CryptoScamDB","severity":1,"path":"/*","hostname":"myetherwallet.compare","ip":"","nameservers":[""],"status":"","statusCode":"","updated":1586531736502,"type":"scam","lookups":[""],"abusereport":"","csdbId":"56645e","addresses":[],"grouped_addresses":{"ETH":null,"BTC":null,"BCH":null,"XRP":null,"TRX":null,"NEO":null,"XMR":null,"LTC":null}}}]}},"pageContext":{"isCreatedByStatefulCreatePages":false,"slug":"56645e"}}