{"data":{"allCsdbScamDomains":{"edges":[{"node":{"id":"Csdb__ScamDomains__8136ab","name":"binance.com87654897.ml","url":"http://binance.com87654897.ml","category":"Phishing","subcategory":"Binance","description":"Fake Binance phishing for logins with POST /submit.php","reporter":"CryptoScamDB","severity":1,"path":"/*","hostname":"binance.com87654897.ml","ip":"","nameservers":[""],"status":"","statusCode":"","updated":1586538939442,"type":"scam","lookups":[""],"abusereport":"","csdbId":"8136ab","addresses":[],"grouped_addresses":{"ETH":null,"BTC":null,"BCH":null,"XRP":null,"TRX":null,"NEO":null,"XMR":null,"LTC":null}}}]}},"pageContext":{"isCreatedByStatefulCreatePages":false,"slug":"8136ab"}}