{"data":{"allCsdbScamDomains":{"edges":[{"node":{"id":"Csdb__ScamDomains__ecbcec","name":"xn--mytherwalet-3qb97c.com","url":"https://xn--mytherwalet-3qb97c.com","category":"Phishing","subcategory":"MyEtherWallet","description":"Fake MyEtherWallet - IDN homograph attack domain. Suspected address: 0x9eEa7Fda3C78cd8C096AE229De8217a94cd1Bcfe 0xA7b8edb0583b478e2b7C431fEb4bc6629a6Cd1E5","reporter":"CryptoScamDB","severity":1,"path":"/*","hostname":"xn--mytherwalet-3qb97c.com","ip":"","nameservers":[""],"status":"","statusCode":"","updated":1586538939441,"type":"scam","lookups":[""],"abusereport":"","csdbId":"ecbcec","addresses":[],"grouped_addresses":{"ETH":null,"BTC":null,"BCH":null,"XRP":null,"TRX":null,"NEO":null,"XMR":null,"LTC":null}}}]}},"pageContext":{"isCreatedByStatefulCreatePages":false,"slug":"ecbcec"}}