{"data":{"allCsdbScamDomains":{"edges":[{"node":{"id":"Csdb__ScamDomains__285d14","name":"dmarket.ltd","url":"http://dmarket.ltd","category":"Phishing","subcategory":"DMarket","description":null,"reporter":"CryptoScamDB","severity":1,"path":"/*","hostname":"dmarket.ltd","ip":"","nameservers":[""],"status":"","statusCode":"","updated":1586538939439,"type":"scam","lookups":[""],"abusereport":"","csdbId":"285d14","addresses":["0xf1e250F2a27ab7eC5B82B287F2799260448CD51D"],"grouped_addresses":{"ETH":["0xf1e250F2a27ab7eC5B82B287F2799260448CD51D"],"BTC":null,"BCH":null,"XRP":null,"TRX":null,"NEO":null,"XMR":null,"LTC":null}}}]}},"pageContext":{"isCreatedByStatefulCreatePages":false,"slug":"285d14"}}