{"data":{"allCsdbScamDomains":{"edges":[{"node":{"id":"Csdb__ScamDomains__0f80b0","name":"wallet-ethereum.org","url":"http://wallet-ethereum.org/","category":"Scam","subcategory":"WebWallet","description":null,"reporter":"CryptoScamDB","severity":1,"path":"/*","hostname":"wallet-ethereum.org","ip":"","nameservers":[""],"status":"","statusCode":"","updated":1586538939439,"type":"scam","lookups":[""],"abusereport":"","csdbId":"0f80b0","addresses":[],"grouped_addresses":{"ETH":null,"BTC":null,"BCH":null,"XRP":null,"TRX":null,"NEO":null,"XMR":null,"LTC":null}}}]}},"pageContext":{"isCreatedByStatefulCreatePages":false,"slug":"0f80b0"}}