{"data":{"allCsdbScamDomains":{"edges":[{"node":{"id":"Csdb__ScamDomains__4162fb","name":"getbigeth.com","url":"http://getbigeth.com","category":"Scamming","subcategory":"Trust-Trading","description":"Trust trading scam site.","reporter":"CryptoScamDB","severity":1,"path":"/*","hostname":"getbigeth.com","ip":"","nameservers":[""],"status":"","statusCode":"","updated":1586538939442,"type":"scam","lookups":[""],"abusereport":"","csdbId":"4162fb","addresses":["0x215e7E7eDEfdA37EB39df17B8b91DA9a60d85530"],"grouped_addresses":{"ETH":["0x215e7E7eDEfdA37EB39df17B8b91DA9a60d85530"],"BTC":null,"BCH":null,"XRP":null,"TRX":null,"NEO":null,"XMR":null,"LTC":null}}}]}},"pageContext":{"isCreatedByStatefulCreatePages":false,"slug":"4162fb"}}