{"data":{"allCsdbScamDomains":{"edges":[{"node":{"id":"Csdb__ScamDomains__706d14","name":"paxful.w3schoolsonline.com","url":"http://paxful.w3schoolsonline.com","category":"Phishing","subcategory":"Paxful","description":"Fake Paxful - kit not fully deployed yet","reporter":"CryptoScamDB","severity":1,"path":"/*","hostname":"paxful.w3schoolsonline.com","ip":"","nameservers":[""],"status":"","statusCode":"","updated":1586538939443,"type":"scam","lookups":[""],"abusereport":"","csdbId":"706d14","addresses":[],"grouped_addresses":{"ETH":null,"BTC":null,"BCH":null,"XRP":null,"TRX":null,"NEO":null,"XMR":null,"LTC":null}}}]}},"pageContext":{"isCreatedByStatefulCreatePages":false,"slug":"706d14"}}