{"data":{"allCsdbScamDomains":{"edges":[{"node":{"id":"Csdb__ScamDomains__13df04","name":"bittrex.cash","url":"http://bittrex.cash/","category":"Phishing","subcategory":"Bittrex","description":null,"reporter":"CryptoScamDB","severity":1,"path":"/*","hostname":"bittrex.cash","ip":"","nameservers":[""],"status":"","statusCode":"","updated":1586538939439,"type":"scam","lookups":[""],"abusereport":"","csdbId":"13df04","addresses":[],"grouped_addresses":{"ETH":null,"BTC":null,"BCH":null,"XRP":null,"TRX":null,"NEO":null,"XMR":null,"LTC":null}}}]}},"pageContext":{"isCreatedByStatefulCreatePages":false,"slug":"13df04"}}