{"data":{"allCsdbScamDomains":{"edges":[{"node":{"id":"Csdb__ScamDomains__e2ecc2","name":"getethereumforfree.com","url":"http://getethereumforfree.com","category":"Scamming","subcategory":"Trust-Trading","description":"Trust trading scam site","reporter":"CryptoScamDB","severity":1,"path":"/*","hostname":"getethereumforfree.com","ip":"","nameservers":[""],"status":"","statusCode":"","updated":1586538939442,"type":"scam","lookups":[""],"abusereport":"","csdbId":"e2ecc2","addresses":["0xC7566BA63f39bA75B56EAdc0328F9A76Dbd1ADf3"],"grouped_addresses":{"ETH":["0xC7566BA63f39bA75B56EAdc0328F9A76Dbd1ADf3"],"BTC":null,"BCH":null,"XRP":null,"TRX":null,"NEO":null,"XMR":null,"LTC":null}}}]}},"pageContext":{"isCreatedByStatefulCreatePages":false,"slug":"0xC7566BA63f39bA75B56EAdc0328F9A76Dbd1ADf3"}}