{"data":{"allCsdbScamDomains":{"edges":[{"node":{"id":"Csdb__ScamDomains__811903","name":"claimd.ethers444.online","url":"https://claimd.ethers444.online","category":"Scamming","subcategory":"Trust-Trading","description":"Trust trading scam site","reporter":"CryptoScamDB","severity":1,"path":"/*","hostname":"claimd.ethers444.online","ip":"","nameservers":[""],"status":"","statusCode":"","updated":1586538939441,"type":"scam","lookups":[""],"abusereport":"","csdbId":"811903","addresses":["0x40949225c4a1745a9946F6AAf763241c082cb9ac"],"grouped_addresses":{"ETH":["0x40949225c4a1745a9946F6AAf763241c082cb9ac"],"BTC":null,"BCH":null,"XRP":null,"TRX":null,"NEO":null,"XMR":null,"LTC":null}}}]}},"pageContext":{"isCreatedByStatefulCreatePages":false,"slug":"811903"}}