{"data":{"allCsdbScamDomains":{"edges":[{"node":{"id":"Csdb__ScamDomains__3cac1d","name":"myetherwallet.xn--rvc1e0am3e","url":"http://myetherwallet.xn--rvc1e0am3e","category":"Phishing","subcategory":"MyEtherWallet","description":null,"reporter":"CryptoScamDB","severity":1,"path":"/*","hostname":"myetherwallet.xn--rvc1e0am3e","ip":"","nameservers":[""],"status":"","statusCode":"","updated":1586538939438,"type":"scam","lookups":[""],"abusereport":"","csdbId":"3cac1d","addresses":[],"grouped_addresses":{"ETH":null,"BTC":null,"BCH":null,"XRP":null,"TRX":null,"NEO":null,"XMR":null,"LTC":null}}}]}},"pageContext":{"isCreatedByStatefulCreatePages":false,"slug":"3cac1d"}}