{"data":{"allCsdbScamDomains":{"edges":[{"node":{"id":"Csdb__ScamDomains__74adc0","name":"bitcoin-pro.club","url":"http://bitcoin-pro.club","category":"Scamming","subcategory":"Trust-Trading","description":"Trust trading scam site - btc doubler","reporter":"CryptoScamDB","severity":1,"path":"/*","hostname":"bitcoin-pro.club","ip":"","nameservers":[""],"status":"","statusCode":"","updated":1586538939443,"type":"scam","lookups":[""],"abusereport":"","csdbId":"74adc0","addresses":["3F5Nc9LyaYveQR3hfKBJHPvc89kVQ3CEKz"],"grouped_addresses":{"ETH":null,"BTC":["3F5Nc9LyaYveQR3hfKBJHPvc89kVQ3CEKz"],"BCH":null,"XRP":null,"TRX":null,"NEO":null,"XMR":null,"LTC":null}}}]}},"pageContext":{"isCreatedByStatefulCreatePages":false,"slug":"74adc0"}}