{"data":{"allCsdbScamDomains":{"edges":[{"node":{"id":"Csdb__ScamDomains__168940","name":"ethereum-code.com","url":"http://ethereum-code.com","category":"Scamming","subcategory":"Pyramid Scheme","description":"Using Ethereum name guaranteeing $10k a week","reporter":"CryptoScamDB","severity":1,"path":"/*","hostname":"ethereum-code.com","ip":"","nameservers":[""],"status":"","statusCode":"","updated":1586538939439,"type":"scam","lookups":[""],"abusereport":"","csdbId":"168940","addresses":[],"grouped_addresses":{"ETH":null,"BTC":null,"BCH":null,"XRP":null,"TRX":null,"NEO":null,"XMR":null,"LTC":null}}}]}},"pageContext":{"isCreatedByStatefulCreatePages":false,"slug":"168940"}}