{"data":{"allCsdbScamDomains":{"edges":[{"node":{"id":"Csdb__ScamDomains__7b2116","name":"bbxotc.tech","url":"http://bbxotc.tech","category":"Scamming","subcategory":"Trust-Trading","description":"Trust trading scam site","reporter":"CryptoScamDB","severity":1,"path":"/*","hostname":"bbxotc.tech","ip":"","nameservers":[""],"status":"","statusCode":"","updated":1586538939443,"type":"scam","lookups":[""],"abusereport":"","csdbId":"7b2116","addresses":["0x8BdA591ac93925f485cd420A47A48EBa87985ea0"],"grouped_addresses":{"ETH":["0x8BdA591ac93925f485cd420A47A48EBa87985ea0"],"BTC":null,"BCH":null,"XRP":null,"TRX":null,"NEO":null,"XMR":null,"LTC":null}}}]}},"pageContext":{"isCreatedByStatefulCreatePages":false,"slug":"7b2116"}}