{"data":{"allCsdbScamDomains":{"edges":[{"node":{"id":"Csdb__ScamDomains__415fca","name":"billaxy.com","url":"http://billaxy.com","category":"Scamming","subcategory":"Exchange","description":"Fake exchange phishing for deposits (promo code gives you 0.25btc) - https://redd.it/d6l97g","reporter":"CryptoScamDB","severity":1,"path":"/*","hostname":"billaxy.com","ip":"","nameservers":[""],"status":"","statusCode":"","updated":1586538939444,"type":"scam","lookups":[""],"abusereport":"","csdbId":"415fca","addresses":["0x5fc2d416388fd1c07ae7e4a10b79a498eb4383c0","17GVN4B8c8BDLJ2e6qMQ9CDwWPGK5vQzi3","qzk0a6gkdgal4nv5t7vgg0ydnrfjwdxuucmlye0vus"],"grouped_addresses":{"ETH":["0x5fc2d416388fd1c07ae7e4a10b79a498eb4383c0"],"BTC":["17GVN4B8c8BDLJ2e6qMQ9CDwWPGK5vQzi3"],"BCH":["qzk0a6gkdgal4nv5t7vgg0ydnrfjwdxuucmlye0vus"],"XRP":null,"TRX":null,"NEO":null,"XMR":null,"LTC":null}}}]}},"pageContext":{"isCreatedByStatefulCreatePages":false,"slug":"415fca"}}