{"data":{"allCsdbScamDomains":{"edges":[{"node":{"id":"Csdb__ScamDomains__c4f830","name":"viberate.bettermost.net","url":"http://viberate.bettermost.net","category":"Phishing","subcategory":"MyEtherWallet","description":"Fake MyEtherWallet. Suspected address: 0x5457Bb4430d8B8D1A3708576100Aef0e027C5b9B","reporter":"CryptoScamDB","severity":1,"path":"/*","hostname":"viberate.bettermost.net","ip":"","nameservers":[""],"status":"","statusCode":"","updated":1586538939441,"type":"scam","lookups":[""],"abusereport":"","csdbId":"c4f830","addresses":[],"grouped_addresses":{"ETH":null,"BTC":null,"BCH":null,"XRP":null,"TRX":null,"NEO":null,"XMR":null,"LTC":null}}}]}},"pageContext":{"isCreatedByStatefulCreatePages":false,"slug":"c4f830"}}