{"data":{"allCsdbScamDomains":{"edges":[{"node":{"id":"Csdb__ScamDomains__a077d0","name":"myetherwallet.xxx","url":"http://myetherwallet.xxx","category":"Phishing","subcategory":"MyEtherWallet","description":null,"reporter":"CryptoScamDB","severity":1,"path":"/*","hostname":"myetherwallet.xxx","ip":"","nameservers":[""],"status":"","statusCode":"","updated":1586538939438,"type":"scam","lookups":[""],"abusereport":"","csdbId":"a077d0","addresses":[],"grouped_addresses":{"ETH":null,"BTC":null,"BCH":null,"XRP":null,"TRX":null,"NEO":null,"XMR":null,"LTC":null}}}]}},"pageContext":{"isCreatedByStatefulCreatePages":false,"slug":"a077d0"}}