{"data":{"allCsdbScamDomains":{"edges":[{"node":{"id":"Csdb__ScamDomains__2bdfc4","name":"giftsforyou.online","url":"http://giftsforyou.online","category":"Scamming","subcategory":"Trust-Trading","description":"Trust trading scam site","reporter":"CryptoScamDB","severity":1,"path":"/*","hostname":"giftsforyou.online","ip":"","nameservers":[""],"status":"","statusCode":"","updated":1586538939442,"type":"scam","lookups":[""],"abusereport":"","csdbId":"2bdfc4","addresses":["0x1707BC69d91F86A6000d318E85D07B00747152FE"],"grouped_addresses":{"ETH":["0x1707BC69d91F86A6000d318E85D07B00747152FE"],"BTC":null,"BCH":null,"XRP":null,"TRX":null,"NEO":null,"XMR":null,"LTC":null}}}]}},"pageContext":{"isCreatedByStatefulCreatePages":false,"slug":"2bdfc4"}}