{"data":{"allCsdbScamDomains":{"edges":[{"node":{"id":"Csdb__ScamDomains__6806b0","name":"login-blockchian.net","url":"http://login-blockchian.net","category":"Phishing","subcategory":"Blockchain","description":"Suspicious Blockchain domain","reporter":"CryptoScamDB","severity":1,"path":"/*","hostname":"login-blockchian.net","ip":"","nameservers":[""],"status":"","statusCode":"","updated":1586538939442,"type":"scam","lookups":[""],"abusereport":"","csdbId":"6806b0","addresses":[],"grouped_addresses":{"ETH":null,"BTC":null,"BCH":null,"XRP":null,"TRX":null,"NEO":null,"XMR":null,"LTC":null}}}]}},"pageContext":{"isCreatedByStatefulCreatePages":false,"slug":"6806b0"}}