{"data":{"allCsdbScamDomains":{"edges":[{"node":{"id":"Csdb__ScamDomains__ebb3f3","name":"myetherwallet.boston","url":"http://myetherwallet.boston","category":"Phishing","subcategory":"MyEtherWallet","description":null,"reporter":"CryptoScamDB","severity":1,"path":"/*","hostname":"myetherwallet.boston","ip":"","nameservers":[""],"status":"","statusCode":"","updated":1586531736502,"type":"scam","lookups":[""],"abusereport":"","csdbId":"ebb3f3","addresses":[],"grouped_addresses":{"ETH":null,"BTC":null,"BCH":null,"XRP":null,"TRX":null,"NEO":null,"XMR":null,"LTC":null}}}]}},"pageContext":{"isCreatedByStatefulCreatePages":false,"slug":"ebb3f3"}}