{"data":{"allCsdbScamDomains":{"edges":[{"node":{"id":"Csdb__ScamDomains__662939","name":"medium-smartcontract.space","url":"http://medium-smartcontract.space","category":"Scamming","subcategory":"Trust-Trading","description":"Trust trading scam site","reporter":"CryptoScamDB","severity":1,"path":"/*","hostname":"medium-smartcontract.space","ip":"","nameservers":[""],"status":"","statusCode":"","updated":1586538939442,"type":"scam","lookups":[""],"abusereport":"","csdbId":"662939","addresses":["0x4d281388B9FA97fC5bC13e8392040EFb661B1962"],"grouped_addresses":{"ETH":["0x4d281388B9FA97fC5bC13e8392040EFb661B1962"],"BTC":null,"BCH":null,"XRP":null,"TRX":null,"NEO":null,"XMR":null,"LTC":null}}}]}},"pageContext":{"isCreatedByStatefulCreatePages":false,"slug":"662939"}}