{"data":{"allCsdbScamDomains":{"edges":[{"node":{"id":"Csdb__ScamDomains__5f69e7","name":"shapeskift.io","url":"http://shapeskift.io","category":"Phishing","subcategory":"Shapeshift","description":"Fake Shapeshift site, iframe 188.227.75.205","reporter":"CryptoScamDB","severity":1,"path":"/*","hostname":"shapeskift.io","ip":"","nameservers":[""],"status":"","statusCode":"","updated":1586538939440,"type":"scam","lookups":[""],"abusereport":"","csdbId":"5f69e7","addresses":[],"grouped_addresses":{"ETH":null,"BTC":null,"BCH":null,"XRP":null,"TRX":null,"NEO":null,"XMR":null,"LTC":null}}}]}},"pageContext":{"isCreatedByStatefulCreatePages":false,"slug":"5f69e7"}}