{"data":{"allCsdbScamDomains":{"edges":[{"node":{"id":"Csdb__ScamDomains__1457c2","name":"enternow.info","url":"http://enternow.info","category":"Scamming","subcategory":"Trust-Trading","description":"Trust trading scam site","reporter":"CryptoScamDB","severity":1,"path":"/*","hostname":"enternow.info","ip":"","nameservers":[""],"status":"","statusCode":"","updated":1586538939442,"type":"scam","lookups":[""],"abusereport":"","csdbId":"1457c2","addresses":["0x015fcA1D09287823e634AE51237ee1eeFF03D9d5"],"grouped_addresses":{"ETH":["0x015fcA1D09287823e634AE51237ee1eeFF03D9d5"],"BTC":null,"BCH":null,"XRP":null,"TRX":null,"NEO":null,"XMR":null,"LTC":null}}}]}},"pageContext":{"isCreatedByStatefulCreatePages":false,"slug":"1457c2"}}