{"data":{"allCsdbScamDomains":{"edges":[{"node":{"id":"Csdb__ScamDomains__ea641e","name":"claim-eth.net","url":"http://claim-eth.net","category":"Scamming","subcategory":"Trust-Trading","description":"Trust trading scam site.","reporter":"CryptoScamDB","severity":1,"path":"/*","hostname":"claim-eth.net","ip":"","nameservers":[""],"status":"","statusCode":"","updated":1586538939442,"type":"scam","lookups":[""],"abusereport":"","csdbId":"ea641e","addresses":["0x31e437cfa7DD0c6bad194e4865c3696551715c4A"],"grouped_addresses":{"ETH":["0x31e437cfa7DD0c6bad194e4865c3696551715c4A"],"BTC":null,"BCH":null,"XRP":null,"TRX":null,"NEO":null,"XMR":null,"LTC":null}}}]}},"pageContext":{"isCreatedByStatefulCreatePages":false,"slug":"ea641e"}}