{"data":{"allCsdbScamDomains":{"edges":[{"node":{"id":"Csdb__ScamDomains__f5ca8c","name":"5000eth-promo.com","url":"https://5000eth-promo.com","category":"Scamming","subcategory":"Trust-Trading","description":"Trust trading scam site","reporter":"CryptoScamDB","severity":1,"path":"/*","hostname":"5000eth-promo.com","ip":"","nameservers":[""],"status":"","statusCode":"","updated":1586538939441,"type":"scam","lookups":[""],"abusereport":"","csdbId":"f5ca8c","addresses":["0xa61344257ed7c98b4690572e63797d75b0753f96"],"grouped_addresses":{"ETH":["0xa61344257ed7c98b4690572e63797d75b0753f96"],"BTC":null,"BCH":null,"XRP":null,"TRX":null,"NEO":null,"XMR":null,"LTC":null}}}]}},"pageContext":{"isCreatedByStatefulCreatePages":false,"slug":"f5ca8c"}}