{"data":{"allCsdbScamDomains":{"edges":[{"node":{"id":"Csdb__ScamDomains__3965f6","name":"xn--hitbt-8xa.com","url":"http://xn--hitbt-8xa.com","category":"Phishing","subcategory":"HitBTC","description":"Fake HitBTC phishing for logins with POST /indexSend.php","reporter":"CryptoScamDB","severity":1,"path":"/*","hostname":"xn--hitbt-8xa.com","ip":"","nameservers":[""],"status":"","statusCode":"","updated":1586538939443,"type":"scam","lookups":[""],"abusereport":"","csdbId":"3965f6","addresses":[],"grouped_addresses":{"ETH":null,"BTC":null,"BCH":null,"XRP":null,"TRX":null,"NEO":null,"XMR":null,"LTC":null}}}]}},"pageContext":{"isCreatedByStatefulCreatePages":false,"slug":"3965f6"}}