{"data":{"allCsdbScamDomains":{"edges":[{"node":{"id":"Csdb__ScamDomains__905985","name":"bonus.ether-gifts.com","url":"http://bonus.ether-gifts.com","category":"Scamming","subcategory":"Trust-Trading","description":"Trust trading scam site","reporter":"CryptoScamDB","severity":1,"path":"/*","hostname":"bonus.ether-gifts.com","ip":"","nameservers":[""],"status":"","statusCode":"","updated":1586538939440,"type":"scam","lookups":[""],"abusereport":"","csdbId":"905985","addresses":["0x64C940690A3660e68D93D8c6412d900BdD3e11E5"],"grouped_addresses":{"ETH":["0x64C940690A3660e68D93D8c6412d900BdD3e11E5"],"BTC":null,"BCH":null,"XRP":null,"TRX":null,"NEO":null,"XMR":null,"LTC":null}}}]}},"pageContext":{"isCreatedByStatefulCreatePages":false,"slug":"0x64C940690A3660e68D93D8c6412d900BdD3e11E5"}}