{"data":{"allCsdbScamDomains":{"edges":[{"node":{"id":"Csdb__ScamDomains__98971b","name":"tokensale.kyber.digital","url":"https://tokensale.kyber.digital","category":"Phishing","subcategory":"Kyber","description":null,"reporter":"CryptoScamDB","severity":1,"path":"/*","hostname":"tokensale.kyber.digital","ip":"","nameservers":[""],"status":"","statusCode":"","updated":1586538939439,"type":"scam","lookups":[""],"abusereport":"","csdbId":"98971b","addresses":["0x7a18cfc4a36e48163034e51a9ed19d4bdea05f6f"],"grouped_addresses":{"ETH":["0x7a18cfc4a36e48163034e51a9ed19d4bdea05f6f"],"BTC":null,"BCH":null,"XRP":null,"TRX":null,"NEO":null,"XMR":null,"LTC":null}}}]}},"pageContext":{"isCreatedByStatefulCreatePages":false,"slug":"0x7a18cfc4a36e48163034e51a9ed19d4bdea05f6f"}}