{"data":{"allCsdbScamDomains":{"edges":[{"node":{"id":"Csdb__ScamDomains__aa0083","name":"reeveclancy.wixsite.com","url":"http://reeveclancy.wixsite.com","category":"Scamming","subcategory":"Trust-trading","description":"Trust-Trading scam (looks like a fake ICO - send ETH and have a 92% chance of winning 100ETH - no contract address)","reporter":"CryptoScamDB","severity":1,"path":"/*","hostname":"reeveclancy.wixsite.com","ip":"","nameservers":[""],"status":"","statusCode":"","updated":1586538939440,"type":"scam","lookups":[""],"abusereport":"","csdbId":"aa0083","addresses":["0x3007a0Db9CAAD557CF4589Cfd550c21ce9399b15"],"grouped_addresses":{"ETH":["0x3007a0Db9CAAD557CF4589Cfd550c21ce9399b15"],"BTC":null,"BCH":null,"XRP":null,"TRX":null,"NEO":null,"XMR":null,"LTC":null}}}]}},"pageContext":{"isCreatedByStatefulCreatePages":false,"slug":"aa0083"}}