{"data":{"allCsdbScamDomains":{"edges":[{"node":{"id":"Csdb__ScamDomains__7da348","name":"cryptogiveaways.top","url":"http://cryptogiveaways.top","category":"Scamming","subcategory":"Trust-Trading","description":"Trust trading scam site","reporter":"CryptoScamDB","severity":1,"path":"/*","hostname":"cryptogiveaways.top","ip":"","nameservers":[""],"status":"","statusCode":"","updated":1586538939443,"type":"scam","lookups":[""],"abusereport":"","csdbId":"7da348","addresses":["1KrXKvZfDUvB9A39xBhJ2VZWf92HMFj8F","0x7a023247e70ad842b0c1226e09185b461a1cd47d"],"grouped_addresses":{"ETH":["0x7a023247e70ad842b0c1226e09185b461a1cd47d"],"BTC":["1KrXKvZfDUvB9A39xBhJ2VZWf92HMFj8F"],"BCH":null,"XRP":null,"TRX":null,"NEO":null,"XMR":null,"LTC":null}}}]}},"pageContext":{"isCreatedByStatefulCreatePages":false,"slug":"7da348"}}