{"data":{"allCsdbScamDomains":{"edges":[{"node":{"id":"Csdb__ScamDomains__1b676d","name":"bnbdexethcampaign.com","url":"http://bnbdexethcampaign.com","category":"Scamming","subcategory":"Trust-Trading","description":"Trust trading scam site","reporter":"CryptoScamDB","severity":1,"path":"/*","hostname":"bnbdexethcampaign.com","ip":"","nameservers":[""],"status":"","statusCode":"","updated":1586538939442,"type":"scam","lookups":[""],"abusereport":"","csdbId":"1b676d","addresses":["0x976B3B64A42cf04d735583004c298aA4E62A913c"],"grouped_addresses":{"ETH":["0x976B3B64A42cf04d735583004c298aA4E62A913c"],"BTC":null,"BCH":null,"XRP":null,"TRX":null,"NEO":null,"XMR":null,"LTC":null}}}]}},"pageContext":{"isCreatedByStatefulCreatePages":false,"slug":"1b676d"}}