{"data":{"allCsdbScamDomains":{"edges":[{"node":{"id":"Csdb__ScamDomains__232169","name":"xn--polonex-ieb.com","url":"http://xn--polonex-ieb.com","category":"Phishing","subcategory":"Poloniex","description":"IDN homograph attack on poloniex exchange","reporter":"CryptoScamDB","severity":1,"path":"/*","hostname":"xn--polonex-ieb.com","ip":"","nameservers":[""],"status":"","statusCode":"","updated":1586538939439,"type":"scam","lookups":[""],"abusereport":"","csdbId":"232169","addresses":[],"grouped_addresses":{"ETH":null,"BTC":null,"BCH":null,"XRP":null,"TRX":null,"NEO":null,"XMR":null,"LTC":null}}}]}},"pageContext":{"isCreatedByStatefulCreatePages":false,"slug":"232169"}}