{"data":{"allCsdbScamDomains":{"edges":[{"node":{"id":"Csdb__ScamDomains__8d40e9","name":"ripiocerdit.network","url":"http://ripiocerdit.network/","category":"Phishing","subcategory":"Ripio","description":null,"reporter":"CryptoScamDB","severity":1,"path":"/*","hostname":"ripiocerdit.network","ip":"","nameservers":[""],"status":"","statusCode":"","updated":1586538939439,"type":"scam","lookups":[""],"abusereport":"","csdbId":"8d40e9","addresses":["0x09faf25e57abd0a401bb5a2341d7f926c389f8d1"],"grouped_addresses":{"ETH":["0x09faf25e57abd0a401bb5a2341d7f926c389f8d1"],"BTC":null,"BCH":null,"XRP":null,"TRX":null,"NEO":null,"XMR":null,"LTC":null}}}]}},"pageContext":{"isCreatedByStatefulCreatePages":false,"slug":"8d40e9"}}