{"data":{"allCsdbScamDomains":{"edges":[{"node":{"id":"Csdb__ScamDomains__ab3375","name":"binancce.ml","url":"http://binancce.ml","category":"Phishing","subcategory":"Binance","description":"Fake Binance login screen","reporter":"CryptoScamDB","severity":1,"path":"/*","hostname":"binancce.ml","ip":"","nameservers":[""],"status":"","statusCode":"","updated":1586538939440,"type":"scam","lookups":[""],"abusereport":"","csdbId":"ab3375","addresses":[],"grouped_addresses":{"ETH":null,"BTC":null,"BCH":null,"XRP":null,"TRX":null,"NEO":null,"XMR":null,"LTC":null}}}]}},"pageContext":{"isCreatedByStatefulCreatePages":false,"slug":"ab3375"}}