{"data":{"allCsdbScamDomains":{"edges":[{"node":{"id":"Csdb__ScamDomains__35d786","name":"xn--btstamp-rfb.net","url":"http://xn--btstamp-rfb.net","category":"Phishing","subcategory":"Bitstamp","description":"Fake bitstamp site - IDN homograph attack","reporter":"CryptoScamDB","severity":1,"path":"/*","hostname":"xn--btstamp-rfb.net","ip":"","nameservers":[""],"status":"","statusCode":"","updated":1586538939439,"type":"scam","lookups":[""],"abusereport":"","csdbId":"35d786","addresses":[],"grouped_addresses":{"ETH":null,"BTC":null,"BCH":null,"XRP":null,"TRX":null,"NEO":null,"XMR":null,"LTC":null}}}]}},"pageContext":{"isCreatedByStatefulCreatePages":false,"slug":"35d786"}}