{"data":{"allCsdbScamDomains":{"edges":[{"node":{"id":"Csdb__ScamDomains__0822ec","name":"ethtake.icu","url":"http://ethtake.icu","category":"Scamming","subcategory":"Trust-Trading","description":"Trust trading scam site","reporter":"CryptoScamDB","severity":1,"path":"/*","hostname":"ethtake.icu","ip":"","nameservers":[""],"status":"","statusCode":"","updated":1586538939442,"type":"scam","lookups":[""],"abusereport":"","csdbId":"0822ec","addresses":["0xF97Cb2b86deE9C33c7624Fd7412889543cCA7F5A","0x33CF1CeE79766595DB0270867B6b9FEb8f30a01E"],"grouped_addresses":{"ETH":["0xF97Cb2b86deE9C33c7624Fd7412889543cCA7F5A","0x33CF1CeE79766595DB0270867B6b9FEb8f30a01E"],"BTC":null,"BCH":null,"XRP":null,"TRX":null,"NEO":null,"XMR":null,"LTC":null}}}]}},"pageContext":{"isCreatedByStatefulCreatePages":false,"slug":"0x33CF1CeE79766595DB0270867B6b9FEb8f30a01E"}}