{"data":{"allCsdbScamDomains":{"edges":[{"node":{"id":"Csdb__ScamDomains__ff3082","name":"airdropxrp.com","url":"http://airdropxrp.com","category":"Scamming","subcategory":"Trust-Trading","description":"Trust trading scam site","reporter":"CryptoScamDB","severity":1,"path":"/*","hostname":"airdropxrp.com","ip":"","nameservers":[""],"status":"","statusCode":"","updated":1586535337979,"type":"scam","lookups":[""],"abusereport":"","csdbId":"ff3082","addresses":["r3Pn8LfWyxDw23z3riTaNm7DZ7VLDVom34"],"grouped_addresses":{"ETH":null,"BTC":null,"BCH":null,"XRP":["r3Pn8LfWyxDw23z3riTaNm7DZ7VLDVom34"],"TRX":null,"NEO":null,"XMR":null,"LTC":null}}}]}},"pageContext":{"isCreatedByStatefulCreatePages":false,"slug":"ff3082"}}