{"data":{"allCsdbScamDomains":{"edges":[{"node":{"id":"Csdb__ScamDomains__87da10","name":"myefherwallet.com","url":"http://myefherwallet.com","category":"Phishing","subcategory":"MyEtherWallet","description":"Replacement","reporter":"CryptoScamDB","severity":1,"path":"/*","hostname":"myefherwallet.com","ip":"","nameservers":[""],"status":"","statusCode":"","updated":1586531736501,"type":"scam","lookups":[""],"abusereport":"","csdbId":"87da10","addresses":[],"grouped_addresses":{"ETH":null,"BTC":null,"BCH":null,"XRP":null,"TRX":null,"NEO":null,"XMR":null,"LTC":null}}}]}},"pageContext":{"isCreatedByStatefulCreatePages":false,"slug":"87da10"}}