{"data":{"allCsdbScamDomains":{"edges":[{"node":{"id":"Csdb__ScamDomains__9651cf","name":"doublebitcoin.cc","url":"http://doublebitcoin.cc","category":"Scamming","subcategory":"Trust-Trading","description":"Trust trading scam site - bitcoin doubler","reporter":"CryptoScamDB","severity":1,"path":"/*","hostname":"doublebitcoin.cc","ip":"","nameservers":[""],"status":"","statusCode":"","updated":1586538939443,"type":"scam","lookups":[""],"abusereport":"","csdbId":"9651cf","addresses":["3FVJwsWDYntJ5ZMDeHoRCHjeiDDeuqsp5P"],"grouped_addresses":{"ETH":null,"BTC":["3FVJwsWDYntJ5ZMDeHoRCHjeiDDeuqsp5P"],"BCH":null,"XRP":null,"TRX":null,"NEO":null,"XMR":null,"LTC":null}}}]}},"pageContext":{"isCreatedByStatefulCreatePages":false,"slug":"3FVJwsWDYntJ5ZMDeHoRCHjeiDDeuqsp5P"}}