{"data":{"allCsdbScamDomains":{"edges":[{"node":{"id":"Csdb__ScamDomains__9a8f37","name":"monetha.me","url":"https://monetha.me","category":"Phishing","subcategory":"Monetha","description":null,"reporter":"CryptoScamDB","severity":1,"path":"/*","hostname":"monetha.me","ip":"","nameservers":[""],"status":"","statusCode":"","updated":1586538939439,"type":"scam","lookups":[""],"abusereport":"","csdbId":"9a8f37","addresses":["0x44A7fF01f7d38c73530C279e19d31527Bdcf8c78"],"grouped_addresses":{"ETH":["0x44A7fF01f7d38c73530C279e19d31527Bdcf8c78"],"BTC":null,"BCH":null,"XRP":null,"TRX":null,"NEO":null,"XMR":null,"LTC":null}}}]}},"pageContext":{"isCreatedByStatefulCreatePages":false,"slug":"9a8f37"}}