{"data":{"allCsdbScamDomains":{"edges":[{"node":{"id":"Csdb__ScamDomains__10da4b","name":"lkralken.com","url":"https://lkralken.com","category":"Phishing","subcategory":"Kraken","description":"Fake Kraken site phishing for logins","reporter":"CryptoScamDB","severity":1,"path":"/*","hostname":"lkralken.com","ip":"","nameservers":[""],"status":"","statusCode":"","updated":1586538939442,"type":"scam","lookups":[""],"abusereport":"","csdbId":"10da4b","addresses":[],"grouped_addresses":{"ETH":null,"BTC":null,"BCH":null,"XRP":null,"TRX":null,"NEO":null,"XMR":null,"LTC":null}}}]}},"pageContext":{"isCreatedByStatefulCreatePages":false,"slug":"10da4b"}}