{"data":{"allCsdbScamDomains":{"edges":[{"node":{"id":"Csdb__ScamDomains__5fd42a","name":"elon2020.online","url":"http://elon2020.online","category":"Scamming","subcategory":"Trust-Trading","description":"Trust trading scam site","reporter":"CryptoScamDB","severity":1,"path":"/*","hostname":"elon2020.online","ip":"","nameservers":[""],"status":"","statusCode":"","updated":1586538939444,"type":"scam","lookups":[""],"abusereport":"","csdbId":"5fd42a","addresses":["1NkoL43EkSHqMHy4BK8ZR3RQSwzTyq8EHj","0x1AB45960fc7C38b5087d2B930A2321b01c2f3CEB"],"grouped_addresses":{"ETH":["0x1AB45960fc7C38b5087d2B930A2321b01c2f3CEB"],"BTC":["1NkoL43EkSHqMHy4BK8ZR3RQSwzTyq8EHj"],"BCH":null,"XRP":null,"TRX":null,"NEO":null,"XMR":null,"LTC":null}}}]}},"pageContext":{"isCreatedByStatefulCreatePages":false,"slug":"1NkoL43EkSHqMHy4BK8ZR3RQSwzTyq8EHj"}}