{"data":{"allCsdbScamDomains":{"edges":[{"node":{"id":"Csdb__ScamDomains__86172f","name":"bitcoingives.info","url":"http://bitcoingives.info","category":"Scamming","subcategory":"Trust-Trading","description":"Trust trading scam site","reporter":"CryptoScamDB","severity":1,"path":"/*","hostname":"bitcoingives.info","ip":"","nameservers":[""],"status":"","statusCode":"","updated":1586535337979,"type":"scam","lookups":[""],"abusereport":"","csdbId":"86172f","addresses":["16aZUGY4c4Nhdvx6vHNF7SajzAqYcXgxez","0x7f0dD36F14f21a10f560caa3d7567f483613BaaF","rGU8WTvKbbF23LsajTf4xt9saAmh48UAuj"],"grouped_addresses":{"ETH":["0x7f0dD36F14f21a10f560caa3d7567f483613BaaF"],"BTC":["16aZUGY4c4Nhdvx6vHNF7SajzAqYcXgxez"],"BCH":null,"XRP":["rGU8WTvKbbF23LsajTf4xt9saAmh48UAuj"],"TRX":null,"NEO":null,"XMR":null,"LTC":null}}}]}},"pageContext":{"isCreatedByStatefulCreatePages":false,"slug":"16aZUGY4c4Nhdvx6vHNF7SajzAqYcXgxez"}}