{"data":{"allCsdbScamDomains":{"edges":[{"node":{"id":"Csdb__ScamDomains__bc6a35","name":"myetherwallet.fox","url":"http://myetherwallet.fox","category":"Phishing","subcategory":"MyEtherWallet","description":null,"reporter":"CryptoScamDB","severity":1,"path":"/*","hostname":"myetherwallet.fox","ip":"","nameservers":[""],"status":"","statusCode":"","updated":1586531736502,"type":"scam","lookups":[""],"abusereport":"","csdbId":"bc6a35","addresses":[],"grouped_addresses":{"ETH":null,"BTC":null,"BCH":null,"XRP":null,"TRX":null,"NEO":null,"XMR":null,"LTC":null}}}]}},"pageContext":{"isCreatedByStatefulCreatePages":false,"slug":"bc6a35"}}