{"data":{"allCsdbScamDomains":{"edges":[{"node":{"id":"Csdb__ScamDomains__9483e3","name":"bountyxrp.blogspot.am","url":"http://bountyxrp.blogspot.am","category":"Scamming","subcategory":"Trust-Trading","description":"Trust trading scam","reporter":"CryptoScamDB","severity":1,"path":"/*","hostname":"bountyxrp.blogspot.am","ip":"","nameservers":[""],"status":"","statusCode":"","updated":1586538939443,"type":"scam","lookups":[""],"abusereport":"","csdbId":"9483e3","addresses":["rhTCdpaZQSKbHNYY85xPLMEWQbyxYr4SFY"],"grouped_addresses":{"ETH":null,"BTC":null,"BCH":null,"XRP":["rhTCdpaZQSKbHNYY85xPLMEWQbyxYr4SFY"],"TRX":null,"NEO":null,"XMR":null,"LTC":null}}}]}},"pageContext":{"isCreatedByStatefulCreatePages":false,"slug":"9483e3"}}