{"data":{"allCsdbScamDomains":{"edges":[{"node":{"id":"Csdb__ScamDomains__2121fc","name":"xn--shapeshft-w5a.com","url":"http://xn--shapeshft-w5a.com","category":"Phishing","subcategory":"Shapeshift","description":"Fake Shapeshift - IDN homograph attack","reporter":"CryptoScamDB","severity":1,"path":"/*","hostname":"xn--shapeshft-w5a.com","ip":"","nameservers":[""],"status":"","statusCode":"","updated":1586538939439,"type":"scam","lookups":[""],"abusereport":"","csdbId":"2121fc","addresses":[],"grouped_addresses":{"ETH":null,"BTC":null,"BCH":null,"XRP":null,"TRX":null,"NEO":null,"XMR":null,"LTC":null}}}]}},"pageContext":{"isCreatedByStatefulCreatePages":false,"slug":"2121fc"}}