{"data":{"allCsdbScamDomains":{"edges":[{"node":{"id":"Csdb__ScamDomains__09c13c","name":"myetherwallet.dev","url":"http://myetherwallet.dev","category":"Phishing","subcategory":"MyEtherWallet","description":null,"reporter":"CryptoScamDB","severity":1,"path":"/*","hostname":"myetherwallet.dev","ip":"","nameservers":[""],"status":"","statusCode":"","updated":1586531736502,"type":"scam","lookups":[""],"abusereport":"","csdbId":"09c13c","addresses":[],"grouped_addresses":{"ETH":null,"BTC":null,"BCH":null,"XRP":null,"TRX":null,"NEO":null,"XMR":null,"LTC":null}}}]}},"pageContext":{"isCreatedByStatefulCreatePages":false,"slug":"09c13c"}}