{"data":{"allCsdbScamDomains":{"edges":[{"node":{"id":"Csdb__ScamDomains__c83b0f","name":"ripple-chain.org","url":"http://ripple-chain.org","category":"Phishing","subcategory":"Ripple","description":"Fake Ripple web wallet","reporter":"CryptoScamDB","severity":1,"path":"/*","hostname":"ripple-chain.org","ip":"","nameservers":[""],"status":"","statusCode":"","updated":1586538939441,"type":"scam","lookups":[""],"abusereport":"","csdbId":"c83b0f","addresses":[],"grouped_addresses":{"ETH":null,"BTC":null,"BCH":null,"XRP":null,"TRX":null,"NEO":null,"XMR":null,"LTC":null}}}]}},"pageContext":{"isCreatedByStatefulCreatePages":false,"slug":"c83b0f"}}