{"data":{"allCsdbScamDomains":{"edges":[{"node":{"id":"Csdb__ScamDomains__b536f6","name":"gowincoin.com","url":"http://gowincoin.com","category":"Scamming","subcategory":"Trust-Trading","description":"Trust trading scam site","reporter":"CryptoScamDB","severity":1,"path":"/*","hostname":"gowincoin.com","ip":"","nameservers":[""],"status":"","statusCode":"","updated":1586538939443,"type":"scam","lookups":[""],"abusereport":"","csdbId":"b536f6","addresses":["1ApXtisCrsykSmzCXsRFL6mhtKQUdN6eQB","0x8583EE650C6566503d1d9DD3FaE76498e7E4CcAA"],"grouped_addresses":{"ETH":["0x8583EE650C6566503d1d9DD3FaE76498e7E4CcAA"],"BTC":["1ApXtisCrsykSmzCXsRFL6mhtKQUdN6eQB"],"BCH":null,"XRP":null,"TRX":null,"NEO":null,"XMR":null,"LTC":null}}}]}},"pageContext":{"isCreatedByStatefulCreatePages":false,"slug":"b536f6"}}