{"data":{"allCsdbScamDomains":{"edges":[{"node":{"id":"Csdb__ScamDomains__d775e9","name":"jyetherwallet.com","url":"http://jyetherwallet.com","category":"Phishing","subcategory":"MyEtherWallet","description":"Replacement","reporter":"CryptoScamDB","severity":1,"path":"/*","hostname":"jyetherwallet.com","ip":"","nameservers":[""],"status":"","statusCode":"","updated":1586531736501,"type":"scam","lookups":[""],"abusereport":"","csdbId":"d775e9","addresses":[],"grouped_addresses":{"ETH":null,"BTC":null,"BCH":null,"XRP":null,"TRX":null,"NEO":null,"XMR":null,"LTC":null}}}]}},"pageContext":{"isCreatedByStatefulCreatePages":false,"slug":"d775e9"}}