{"data":{"allCsdbScamDomains":{"edges":[{"node":{"id":"Csdb__ScamDomains__8c83b4","name":"coineplus.com","url":"https://coineplus.com","category":"Phishing","subcategory":"Exchange","description":"Fake Exchange","reporter":"CryptoScamDB","severity":1,"path":"/*","hostname":"coineplus.com","ip":"","nameservers":[""],"status":"","statusCode":"","updated":1586538939443,"type":"scam","lookups":[""],"abusereport":"","csdbId":"8c83b4","addresses":["31tdhvgYpkJoMpJs75pkzcp27GpATwYsHc","0x4A7D4264291d6bEe4D4Ee3EB01006445e19EF366"],"grouped_addresses":{"ETH":["0x4A7D4264291d6bEe4D4Ee3EB01006445e19EF366"],"BTC":["31tdhvgYpkJoMpJs75pkzcp27GpATwYsHc"],"BCH":null,"XRP":null,"TRX":null,"NEO":null,"XMR":null,"LTC":null}}}]}},"pageContext":{"isCreatedByStatefulCreatePages":false,"slug":"8c83b4"}}