{"data":{"allCsdbScamDomains":{"edges":[{"node":{"id":"Csdb__ScamDomains__d68a99","name":"bigpromo.net","url":"http://bigpromo.net","category":"Scamming","subcategory":"Trust-Trading","description":"Trust trading scam site","reporter":"CryptoScamDB","severity":1,"path":"/*","hostname":"bigpromo.net","ip":"","nameservers":[""],"status":"","statusCode":"","updated":1586535337979,"type":"scam","lookups":[""],"abusereport":"","csdbId":"d68a99","addresses":["1ANV91xkSF1QGos5SGxuxxED6ZVx4L8bra"],"grouped_addresses":{"ETH":null,"BTC":["1ANV91xkSF1QGos5SGxuxxED6ZVx4L8bra"],"BCH":null,"XRP":null,"TRX":null,"NEO":null,"XMR":null,"LTC":null}}}]}},"pageContext":{"isCreatedByStatefulCreatePages":false,"slug":"d68a99"}}