{"data":{"allCsdbScamDomains":{"edges":[{"node":{"id":"Csdb__ScamDomains__ff7dc7","name":"ether-give.com","url":"https://ether-give.com","category":"Scamming","subcategory":"Trust-Trading","description":"Trust trading scam site","reporter":"CryptoScamDB","severity":1,"path":"/*","hostname":"ether-give.com","ip":"","nameservers":[""],"status":"","statusCode":"","updated":1586538939441,"type":"scam","lookups":[""],"abusereport":"","csdbId":"ff7dc7","addresses":["0x4360325de602B56F9Ec7F9A88Cef909F249d5677"],"grouped_addresses":{"ETH":["0x4360325de602B56F9Ec7F9A88Cef909F249d5677"],"BTC":null,"BCH":null,"XRP":null,"TRX":null,"NEO":null,"XMR":null,"LTC":null}}}]}},"pageContext":{"isCreatedByStatefulCreatePages":false,"slug":"ff7dc7"}}