{"data":{"allCsdbScamDomains":{"edges":[{"node":{"id":"Csdb__ScamDomains__45a9c9","name":"enigma-tokens.co","url":"https://enigma-tokens.co","category":"Phishing","subcategory":"Engima","description":null,"reporter":"CryptoScamDB","severity":1,"path":"/*","hostname":"enigma-tokens.co","ip":"","nameservers":[""],"status":"","statusCode":"","updated":1586538939439,"type":"scam","lookups":[""],"abusereport":"","csdbId":"45a9c9","addresses":["0x2D4498a2CF71F5b0946f0ebcfff97ca9D0cd5D04"],"grouped_addresses":{"ETH":["0x2D4498a2CF71F5b0946f0ebcfff97ca9D0cd5D04"],"BTC":null,"BCH":null,"XRP":null,"TRX":null,"NEO":null,"XMR":null,"LTC":null}}}]}},"pageContext":{"isCreatedByStatefulCreatePages":false,"slug":"45a9c9"}}