{"data":{"allCsdbScamDomains":{"edges":[{"node":{"id":"Csdb__ScamDomains__9663a3","name":"calibra-token.info","url":"http://calibra-token.info","category":"Phishing","subcategory":"Libra","description":"Fake Calibra crowdsale site","reporter":"CryptoScamDB","severity":1,"path":"/*","hostname":"calibra-token.info","ip":"","nameservers":[""],"status":"","statusCode":"","updated":1586535337979,"type":"scam","lookups":[""],"abusereport":"","csdbId":"9663a3","addresses":["0xdd68910e9fc5b71d4f0f5eceb4ec57742bcc3cd5","1PSHt9agWavn4mf44d8rH6HPfaVpkdV75A (btc)"],"grouped_addresses":{"ETH":["0xdd68910e9fc5b71d4f0f5eceb4ec57742bcc3cd5"],"BTC":["1PSHt9agWavn4mf44d8rH6HPfaVpkdV75A (btc)"],"BCH":null,"XRP":null,"TRX":null,"NEO":null,"XMR":null,"LTC":null}}}]}},"pageContext":{"isCreatedByStatefulCreatePages":false,"slug":"1PSHt9agWavn4mf44d8rH6HPfaVpkdV75A (btc)"}}