{"data":{"allCsdbScamDomains":{"edges":[{"node":{"id":"Csdb__ScamDomains__a5b74c","name":"ethdrop.me","url":"http://ethdrop.me","category":"Scamming","subcategory":"Trust-Trading","description":"Trust trading scam site","reporter":"CryptoScamDB","severity":1,"path":"/*","hostname":"ethdrop.me","ip":"","nameservers":[""],"status":"","statusCode":"","updated":1586535337980,"type":"scam","lookups":[""],"abusereport":"","csdbId":"a5b74c","addresses":["0x9205ddb511303ab460698085fdaac7a81cbd93d4"],"grouped_addresses":{"ETH":["0x9205ddb511303ab460698085fdaac7a81cbd93d4"],"BTC":null,"BCH":null,"XRP":null,"TRX":null,"NEO":null,"XMR":null,"LTC":null}}}]}},"pageContext":{"isCreatedByStatefulCreatePages":false,"slug":"0x9205ddb511303ab460698085fdaac7a81cbd93d4"}}