{"data":{"allCsdbScamDomains":{"edges":[{"node":{"id":"Csdb__ScamDomains__025a56","name":"myetherwallet.liaison","url":"http://myetherwallet.liaison","category":"Phishing","subcategory":"MyEtherWallet","description":null,"reporter":"CryptoScamDB","severity":1,"path":"/*","hostname":"myetherwallet.liaison","ip":"","nameservers":[""],"status":"","statusCode":"","updated":1586531736503,"type":"scam","lookups":[""],"abusereport":"","csdbId":"025a56","addresses":[],"grouped_addresses":{"ETH":null,"BTC":null,"BCH":null,"XRP":null,"TRX":null,"NEO":null,"XMR":null,"LTC":null}}}]}},"pageContext":{"isCreatedByStatefulCreatePages":false,"slug":"025a56"}}