{"data":{"allCsdbScamDomains":{"edges":[{"node":{"id":"Csdb__ScamDomains__43ee06","name":"eventmusk.com","url":"http://eventmusk.com","category":"Scamming","subcategory":"Trust-Trading","description":"Trust trading scam site","reporter":"CryptoScamDB","severity":1,"path":"/*","hostname":"eventmusk.com","ip":"","nameservers":[""],"status":"","statusCode":"","updated":1586538939444,"type":"scam","lookups":[""],"abusereport":"","csdbId":"43ee06","addresses":["16kM6uthkWK8bjySfDXgpF27MdTHHd4Mvq","0x7B4952E2cc3BFcd67174e5543A4aF80475249fCD"],"grouped_addresses":{"ETH":["0x7B4952E2cc3BFcd67174e5543A4aF80475249fCD"],"BTC":["16kM6uthkWK8bjySfDXgpF27MdTHHd4Mvq"],"BCH":null,"XRP":null,"TRX":null,"NEO":null,"XMR":null,"LTC":null}}},{"node":{"id":"Csdb__ScamDomains__b6cc9a","name":"muskevent.info","url":"http://muskevent.info","category":"Scamming","subcategory":"Trust-Trading","description":"Trust trading scam site","reporter":"CryptoScamDB","severity":1,"path":"/*","hostname":"muskevent.info","ip":"","nameservers":[""],"status":"","statusCode":"","updated":1586538939444,"type":"scam","lookups":[""],"abusereport":"","csdbId":"b6cc9a","addresses":["16kM6uthkWK8bjySfDXgpF27MdTHHd4Mvq","0xdc45FDBa6db6bA5eBF7699DF07C118312Cea9422"],"grouped_addresses":{"ETH":["0xdc45FDBa6db6bA5eBF7699DF07C118312Cea9422"],"BTC":["16kM6uthkWK8bjySfDXgpF27MdTHHd4Mvq"],"BCH":null,"XRP":null,"TRX":null,"NEO":null,"XMR":null,"LTC":null}}}]}},"pageContext":{"isCreatedByStatefulCreatePages":false,"slug":"16kM6uthkWK8bjySfDXgpF27MdTHHd4Mvq"}}