{"data":{"allCsdbScamDomains":{"edges":[{"node":{"id":"Csdb__ScamDomains__d804df","name":"xn--myeherwallet-fpc.com","url":"http://xn--myeherwallet-fpc.com","category":"Phishing","subcategory":"MyEtherWallet","description":"Suspicious MyEtherWallet domain (Namecheap default page)","reporter":"CryptoScamDB","severity":1,"path":"/*","hostname":"xn--myeherwallet-fpc.com","ip":"","nameservers":[""],"status":"","statusCode":"","updated":1586538939443,"type":"scam","lookups":[""],"abusereport":"","csdbId":"d804df","addresses":[],"grouped_addresses":{"ETH":null,"BTC":null,"BCH":null,"XRP":null,"TRX":null,"NEO":null,"XMR":null,"LTC":null}}}]}},"pageContext":{"isCreatedByStatefulCreatePages":false,"slug":"d804df"}}