{"data":{"allCsdbScamDomains":{"edges":[{"node":{"id":"Csdb__ScamDomains__95958f","name":"ethsafe.info","url":"http://ethsafe.info","category":"Scamming","subcategory":"Trust-Trading","description":"Trust trading scam site.","reporter":"CryptoScamDB","severity":1,"path":"/*","hostname":"ethsafe.info","ip":"","nameservers":[""],"status":"","statusCode":"","updated":1586538939442,"type":"scam","lookups":[""],"abusereport":"","csdbId":"95958f","addresses":["0x1cBc864EA74e0f23F103dF8623Ba56a01b1eDa59"],"grouped_addresses":{"ETH":["0x1cBc864EA74e0f23F103dF8623Ba56a01b1eDa59"],"BTC":null,"BCH":null,"XRP":null,"TRX":null,"NEO":null,"XMR":null,"LTC":null}}}]}},"pageContext":{"isCreatedByStatefulCreatePages":false,"slug":"95958f"}}