{"data":{"allCsdbScamDomains":{"edges":[{"node":{"id":"Csdb__ScamDomains__5d2fed","name":"muskgive.info","url":"http://muskgive.info","category":"Scamming","subcategory":"Trust-Trading","description":"Trust trading scam site","reporter":"CryptoScamDB","severity":1,"path":"/*","hostname":"muskgive.info","ip":"","nameservers":[""],"status":"","statusCode":"","updated":1586535337980,"type":"scam","lookups":[""],"abusereport":"","csdbId":"5d2fed","addresses":["14uvhgFCCCCnPDDj6g3CojPrfCy8JEmBsi","0x2df0dab68d148c53b9b1666f8dc044680860d2e7"],"grouped_addresses":{"ETH":["0x2df0dab68d148c53b9b1666f8dc044680860d2e7"],"BTC":["14uvhgFCCCCnPDDj6g3CojPrfCy8JEmBsi"],"BCH":null,"XRP":null,"TRX":null,"NEO":null,"XMR":null,"LTC":null}}}]}},"pageContext":{"isCreatedByStatefulCreatePages":false,"slug":"14uvhgFCCCCnPDDj6g3CojPrfCy8JEmBsi"}}