{"data":{"allCsdbScamDomains":{"edges":[{"node":{"id":"Csdb__ScamDomains__4d5e4f","name":"get-5000eth.com","url":"http://get-5000eth.com","category":"Scamming","subcategory":"Trust-Trading","description":"Trust trading scam site","reporter":"CryptoScamDB","severity":1,"path":"/*","hostname":"get-5000eth.com","ip":"","nameservers":[""],"status":"","statusCode":"","updated":1586538939440,"type":"scam","lookups":[""],"abusereport":"","csdbId":"4d5e4f","addresses":["0x5093c4029aCab3AfF80140023099F5Ec6ca7D52F"],"grouped_addresses":{"ETH":["0x5093c4029aCab3AfF80140023099F5Ec6ca7D52F"],"BTC":null,"BCH":null,"XRP":null,"TRX":null,"NEO":null,"XMR":null,"LTC":null}}}]}},"pageContext":{"isCreatedByStatefulCreatePages":false,"slug":"0x5093c4029aCab3AfF80140023099F5Ec6ca7D52F"}}